{
  "steer": "Steer",
  "map2d": "2D Map",
  "camera": "Camera",
    "screenshot": "Screenshot",
  "configuration": "Configuration",
  "chat": "Chat",
  "recorder": "Screen Recording",
  "takeoff": "Takeoff",
  "landing": "Landing",
  "taking_off": "Taking Off...",
  "landing_in_progress": "Landing...",
  "pages": "Pages",
  "page_aerial": "3D Aerial",
  "page_mesh": "3D Mesh",
  "page_3dgs": "3DGS",
  "page_map": "2D Map",
  "page_satellite": "2D Satellite",
  "page_chat": "Community",
  "page_customer_service": "Customer Service",
  "page_settings": "Settings",
  "page_myspace": "My Space",
  "page_extensions": "Extensions",
  
  "settings_language": "Language",
  "settings_font": "Font",
  "settings_font_style": "Font Style",
  "settings_font_size": "Font Size",
  "settings_media": "Media",
  "settings_audio_volume": "Audio Volume",
  "settings_network": "Network",
  "settings_enterprise_proxy": "Enterprise Proxy",
  "settings_enterprise_proxy_placeholder": "https://192.168.0.1:3128",
  "settings_proxy_reminder_prefix": "These settings are configured by 'simple-squid-proxy' extension,",
  "settings_proxy_reminder_link": "click here",
  "settings_proxy_reminder_suffix": "to change the settings.",
  "settings_flight": "Flight",
  "settings_reset_defaults": "Reset to Defaults",
  "settings_takeoff_altitude": "Takeoff Altitude (m)",
  "calibrating": "Calibrating...",
  "preparing_takeoff": "Preparing takeoff...",
  "obstacle_above": "Obstacle detected above. Please move the drone to continue.",
  "obstacle_below": "Obstacle detected below. Please move the drone to continue.",
  "recorder_locked": "Recorder is locked during auto sequence.",
  "scanning_landing": "Scanning landing zone...",
  "settings_safety_buffer": "Safety Buffer (m)",
  "settings_default_lat": "Initial Latitude",
  "settings_default_lon": "Initial Longitude",
  "settings_default_alt": "Initial Altitude (m)",
  "settings_default_yaw": "Initial Z (yaw)",
  "settings_default_pitch": "Initial Y (pitch)",
  "settings_default_roll": "Initial X (roll)",
  "waypoint": "Waypoint",
  "waypoint_destination": "Destination",
  "waypoint_origin": "Origin",
  "waypoint_origin_placeholder": "type in or tap map",
  "waypoint_tag_title": "Select origin from map",
  "waypoint_increase_index": "Reorder the waypoints",
  "waypoint_delete": "Delete this waypoint",
  "waypoint_search_waypoint": "Search waypoints",
  "waypoint_search_routes": "Search route",
  "waypoint_route_need_more": "Please add at least two waypoints to search for a route.",
  "waypoint_route_error": "Could not find a route. Please check the waypoints.",
  "waypoint_go_to_origin": "Go to the origin",
  "waypoint_poi_types": "Types",
  "waypoint_poi_rating": "Rating",
  "waypoint_poi_vicinity": "Address",
  "waypoint_poi_no_results": "POIs or Route",
  "extensions_scenic": "Scenic Tour",
  "extensions_swarm": "Swarm Coordination",
  "extensions_real_drone": "Real Drone",
  "extensions_hardware": "Hardware",
  "extensions_software": "Software",
  "extensions_search_placeholder": "Search extensions...",
  "extensions_sub_network": "Network",
  "extensions_simple_squid_proxy": "Simple Squid Proxy"
}
